README.rst
setup.py
pyknotid/__init__.py
pyknotid/cinvariants.c
pyknotid/cinvariants.pyx
pyknotid/invariants.py
pyknotid/io.py
pyknotid/utils.py
pyknotid/visualcollection.py
pyknotid/visualise.py
pyknotid/writhes.py
pyknotid.egg-info/PKG-INFO
pyknotid.egg-info/SOURCES.txt
pyknotid.egg-info/dependency_links.txt
pyknotid.egg-info/entry_points.txt
pyknotid.egg-info/requires.txt
pyknotid.egg-info/top_level.txt
pyknotid/catalogue/__init__.py
pyknotid/catalogue/build.py
pyknotid/catalogue/converters.py
pyknotid/catalogue/database.py
pyknotid/catalogue/getdb.py
pyknotid/catalogue/identify.py
pyknotid/catalogue/improve.py
pyknotid/cli/__init__.py
pyknotid/cli/analyse_knot_file.py
pyknotid/cli/plot_knot.py
pyknotid/make/__init__.py
pyknotid/make/named.py
pyknotid/make/periodic_knot.py
pyknotid/make/torus.py
pyknotid/representations/__init__.py
pyknotid/representations/dtnotation.py
pyknotid/representations/gausscode.py
pyknotid/representations/gaussdiagram.py
pyknotid/representations/planardiagram.py
pyknotid/representations/representation.py
pyknotid/simplify/__init__.py
pyknotid/simplify/coctree.c
pyknotid/simplify/coctree.pyx
pyknotid/simplify/octree.py
pyknotid/spacecurves/__init__.py
pyknotid/spacecurves/ccomplexity.c
pyknotid/spacecurves/ccomplexity.pyx
pyknotid/spacecurves/chelpers.c
pyknotid/spacecurves/chelpers.pyx
pyknotid/spacecurves/complexity.py
pyknotid/spacecurves/geometry.py
pyknotid/spacecurves/helpers.py
pyknotid/spacecurves/knot.py
pyknotid/spacecurves/link.py
pyknotid/spacecurves/openknot.py
pyknotid/spacecurves/periodic.py
pyknotid/spacecurves/periodiccell.py
pyknotid/spacecurves/periodicline.py
pyknotid/spacecurves/rotation.py
pyknotid/spacecurves/setup.py
pyknotid/spacecurves/smooth.py
pyknotid/spacecurves/spacecurve.py