Metadata-Version: 1.0
Name: pyknotid
Version: 0.5.3
Summary: Tools for identifying and analysing knots, in space-curves or standard topological representations
Home-page: UNKNOWN
Author: Alexander Taylor
Author-email: alexander.taylor@bristol.ac.uk
License: UNKNOWN
Platform: UNKNOWN
